ucr/__init__.py
ucr/conf/architecture/cls_ppocr_mobile.yaml
ucr/conf/architecture/det_mv3_db.yaml
ucr/conf/architecture/det_mv3_east.yaml
ucr/conf/architecture/det_ppocr_mobile.yaml
ucr/conf/architecture/det_ppocr_server.yaml
ucr/conf/architecture/det_r50_vd_db.yaml
ucr/conf/architecture/det_r50_vd_east.yaml
ucr/conf/architecture/det_r50_vd_sast_icdar15.yaml
ucr/conf/architecture/det_r50_vd_sast_totaltext.yaml
ucr/conf/architecture/det_vgg_craft.yaml
ucr/conf/architecture/rec_icdar15.yaml
ucr/conf/architecture/rec_mv3_none_bilstm_ctc.yaml
ucr/conf/architecture/rec_mv3_none_none_ctc.yaml
ucr/conf/architecture/rec_mv3_tps_bilstm_att.yaml
ucr/conf/architecture/rec_mv3_tps_bilstm_ctc.yaml
ucr/conf/architecture/rec_ppocr_mobile.yaml
ucr/conf/architecture/rec_ppocr_server.yaml
ucr/conf/architecture/rec_r34_vd_none_bilstm_ctc.yaml
ucr/conf/architecture/rec_r34_vd_none_none_ctc.yaml
ucr/conf/architecture/rec_r34_vd_tps_bilstm_att.yaml
ucr/conf/architecture/rec_r34_vd_tps_bilstm_ctc.yaml
ucr/conf/architecture/rec_r50_fpn_srn.yaml
ucr/conf/hydra/job_logging/custom.yaml
ucr/conf/hydra/output/custom.yaml
ucr/conf/infer_cls.yaml
ucr/conf/infer_det.yaml
ucr/conf/infer_rec.yaml
ucr/conf/infer_system.yaml
ucr/conf/postprocess/cls.yaml
ucr/conf/postprocess/det_craft.yaml
ucr/conf/postprocess/det_db.yaml
ucr/conf/postprocess/det_east.yaml
ucr/conf/postprocess/det_sast_icdar15.yaml
ucr/conf/postprocess/det_sast_totaltext.yaml
ucr/conf/postprocess/rec_att.yaml
ucr/conf/postprocess/rec_ctc.yaml
ucr/conf/postprocess/rec_srn.yaml
ucr/conf/preprocess/cls.yaml
ucr/conf/preprocess/det_craft.yaml
ucr/conf/preprocess/det_db.yaml
ucr/conf/preprocess/det_east.yaml
ucr/conf/preprocess/det_sast_icdar15.yaml
ucr/conf/preprocess/det_sast_totaltext.yaml
ucr/conf/preprocess/rec_att.yaml
ucr/conf/preprocess/rec_ctc.yaml
ucr/conf/preprocess/rec_srn.yaml
ucr/core/__init__.py
ucr/core/architecture/__init__.py
ucr/core/architecture/backbone/__init__.py
ucr/core/architecture/backbone/det_mobilenet_v3.py
ucr-0.2.16.dist-info/entry_points.txt
ucr-0.2.16.dist-info/LICENSE
ucr-0.2.16.dist-info/WHEEL
ucr-0.2.16.dist-info/METADATA
ucr-0.2.16.dist-info/RECORD
