Metadata-Version: 2.1
Name: ucr
Version: 0.2.16
Summary: Universal Character Recognizer (UCR): Simple, Intuitive, Extensible, Multi-Lingual OCR engine
Author: Abhigyan Raman
Author-email: abhigyan@docyard.ai
Requires-Python: >=3.6.2,<4.0.0
Classifier: Programming Language :: Python :: 3
Classifier: Programming Language :: Python :: 3.7
Classifier: Programming Language :: Python :: 3.8
Classifier: Programming Language :: Python :: 3.9
Requires-Dist: PyMuPDF (>=1.18.10,<2.0.0)
Requires-Dist: hydra-core (>=1.0.6,<2.0.0)
Requires-Dist: imgaug (>=0.4.0,<0.5.0)
Requires-Dist: numpy (<1.20.0)
Requires-Dist: opencv-python (>=4.1.0,<5.0.0)
Requires-Dist: pandas (>=1.1,<1.2)
Requires-Dist: pyclipper (>=1.2.1,<2.0.0)
Requires-Dist: tabulate (>=0.8.9,<0.9.0)
Requires-Dist: tqdm (>=4.50,<5.0)
Project-URL: Documentation, https://github.com/DocYard-ai/UCR
